getscraping/__init__.py
getscraping/client.py
getscraping/models.py
getscraping-1.0.6.dist-info/LICENSE
getscraping-1.0.6.dist-info/METADATA
getscraping-1.0.6.dist-info/WHEEL
getscraping-1.0.6.dist-info/top_level.txt
getscraping-1.0.6.dist-info/RECORD
