Metadata-Version: 2.1
Name: getscraping
Version: 1.0.6
Summary: Python SDK for the GetScraping API
Author-email: Bart Hough <hello@getscraping.com>
License: GNU GENERAL PUBLIC LICENSE
Project-URL: Homepage, https://getscraping.com/
Project-URL: repository, https://github.com/GetScraping/get-scraping-python
Project-URL: documentation, https://getscraping.com/docs
Keywords: web scraping,crawler,tutorial,beautifulsoup,scraperapi,scrapingbee
Classifier: License :: OSI Approved :: GNU General Public License (GPL)
Classifier: Framework :: Scrapy
Classifier: Programming Language :: Python
Classifier: Programming Language :: Python :: 3
Requires-Python: >=3.6
License-File: LICENSE
Requires-Dist: requests>=2.0.0
Requires-Dist: bs4
Requires-Dist: pydantic>=2.0.0
Provides-Extra: dev
Requires-Dist: pytest; extra == "dev"
Requires-Dist: responses; extra == "dev"
